pihole_api/__init__.py
pihole_api/_core.py
pihole_api/_dns.py
pihole_api/_list.py
pihole_api/_main.py
pi_hole_api-0.1.5.dist-info/LICENSE
pi_hole_api-0.1.5.dist-info/METADATA
pi_hole_api-0.1.5.dist-info/WHEEL
pi_hole_api-0.1.5.dist-info/top_level.txt
pi_hole_api-0.1.5.dist-info/RECORD
