Metadata-Version: 2.1
Name: pi-hole-api
Version: 0.1.5
Summary: API for pihole
Home-page: https://github.com/XelK/pihole_api
Author: Oleksandr Kubashov
Author-email: okubashov@gmail.com
License: UNKNOWN
Project-URL: Bug Tracker, https://github.com/XelK/pihole_api/issues
Platform: UNKNOWN
Classifier: Programming Language :: Python :: 3
Classifier: License :: OSI Approved :: MIT License
Classifier: Operating System :: OS Independent
Requires-Python: >=3.6
License-File: LICENSE
Requires-Dist: requests
